sampleRedis/__init__.py
sampleRedis/ct_cache.py
sample_custom-0.0.2.dist-info/METADATA
sample_custom-0.0.2.dist-info/WHEEL
sample_custom-0.0.2.dist-info/top_level.txt
sample_custom-0.0.2.dist-info/RECORD
